README.rst
confcollect.py
setup.py
confcollect.egg-info/PKG-INFO
confcollect.egg-info/SOURCES.txt
confcollect.egg-info/dependency_links.txt
confcollect.egg-info/requires.txt
confcollect.egg-info/top_level.txt
confcollect.egg-info/zip-safe