Metadata-Version: 1.1
Name: confcollect
Version: 0.3.1
Summary: Helpers to collect configuration from os environment, files etc.
Home-page: https://github.com/miracle2k/confcollect
Author: Michael Elsdoerfer
Author-email: michael@elsdoerfer.com
License: BSD
Platform: UNKNOWN
Classifier: Development Status :: 2 - Pre-Alpha
Classifier: Environment :: Web Environment
Classifier: License :: OSI Approved :: BSD License
